{
  "KIP-98": [
    {
      "id": "KIP-679",
      "score": 0.9241
    },
    {
      "id": "KIP-932",
      "score": 0.8885
    },
    {
      "id": "KIP-392",
      "score": 0.8661
    }
  ],
  "KIP-101": [
    {
      "id": "KIP-392",
      "score": 0.8793
    },
    {
      "id": "KIP-848",
      "score": 0.8655
    },
    {
      "id": "KIP-500",
      "score": 0.8591
    }
  ],
  "KIP-227": [
    {
      "id": "KIP-392",
      "score": 0.8933
    },
    {
      "id": "KIP-848",
      "score": 0.8767
    },
    {
      "id": "KIP-405",
      "score": 0.8759
    }
  ],
  "KIP-392": [
    {
      "id": "KIP-227",
      "score": 0.8933
    },
    {
      "id": "KIP-932",
      "score": 0.8868
    },
    {
      "id": "KIP-405",
      "score": 0.8827
    }
  ],
  "KIP-405": [
    {
      "id": "KIP-932",
      "score": 0.8869
    },
    {
      "id": "KIP-392",
      "score": 0.8827
    },
    {
      "id": "KIP-227",
      "score": 0.8759
    }
  ],
  "KIP-500": [
    {
      "id": "KIP-405",
      "score": 0.8695
    },
    {
      "id": "KIP-932",
      "score": 0.8619
    },
    {
      "id": "KIP-98",
      "score": 0.8611
    }
  ],
  "KIP-679": [
    {
      "id": "KIP-98",
      "score": 0.9241
    },
    {
      "id": "KIP-932",
      "score": 0.8679
    },
    {
      "id": "KIP-392",
      "score": 0.8611
    }
  ],
  "KIP-848": [
    {
      "id": "KIP-392",
      "score": 0.8789
    },
    {
      "id": "KIP-227",
      "score": 0.8767
    },
    {
      "id": "KIP-932",
      "score": 0.867
    }
  ],
  "KIP-932": [
    {
      "id": "KIP-98",
      "score": 0.8885
    },
    {
      "id": "KIP-405",
      "score": 0.8869
    },
    {
      "id": "KIP-392",
      "score": 0.8868
    }
  ]
}
